genice2_svg/__init__.py
genice2_svg/render_png.py
genice2_svg/render_svg.py
genice2_svg/theochem.py
genice2_svg/formats/__init__.py
genice2_svg/formats/png.py
genice2_svg/formats/svg.py
genice2_svg-2.2.dist-info/METADATA
genice2_svg-2.2.dist-info/WHEEL
genice2_svg-2.2.dist-info/entry_points.txt
genice2_svg-2.2.dist-info/top_level.txt
genice2_svg-2.2.dist-info/RECORD
