Metadata-Version: 2.1
Name: genice2-svg
Version: 2.2
Summary: SVG format plugin for GenIce.
Home-page: https://github.com/vitroid/genice-svg/
Author: Masakazu Matsumoto
Author-email: vitroid@gmail.com
License: MIT
Keywords: genice,SVG
Platform: UNKNOWN
Classifier: Development Status :: 4 - Beta
Classifier: Intended Audience :: Developers
Classifier: Programming Language :: Python
Classifier: Programming Language :: Python :: 3.6
Requires-Dist: svgwrite
Requires-Dist: genice2 (>=2.1b0)
Requires-Dist: pillow
Requires-Dist: cycless
